Workbook

Sheet Dashboard
B1: TexaWave ERP - Finance API Test Status Dashboard
B2: Suite: Postman Finance Operations (Payments Received, Expenses & Security Checks) | As of 24-Oct-2026
B4: Total Tasks | D4: Completed | F4: % Tests Done | H4: Blocked | J4: Need to Discuss / Fail | L4: Pending
B5: =COUNTA('Payments Received API'!$A$5:$A$23)+COUNTA('Expenses API'!$A$5:$A$14)+COUNTA('Pending API Checks'!$A$5:$A$19) -> 44 | D5: =COUNTIF('Payments Received API'!$H$5:$H$23,"Completed")+COUNTIF('Payments Received API'!$H$5:$H$23,"PASS")+COUNTIF('Expenses API'!$H$5:$H$14,"Completed")+COUNTIF('Expenses API'!$H$5:$H$14,"PASS")+COUNTIF('Pending API Checks'!$H$5:$H$19,"Completed")+COUNTIF('Pending API Checks'!$H$5:$H$19,"PASS") -> 30 | F5: =IFERROR(AVERAGE('Payments Received API'!$I$5:$I$23,'Expenses API'!$I$5:$I$14,'Pending API Checks'!$I$5:$I$19),0) -> 0.68181818 | H5: =COUNTIF('Payments Received API'!$H$5:$H$23,"Blocked")+COUNTIF('Payments Received API'!$H$5:$H$23,"BLOCKED")+COUNTIF('Expenses API'!$H$5:$H$14,"Blocked")+COUNTIF('Expenses API'!$H$5:$H$14,"BLOCKED")+COUNTIF('Pending API Checks'!$H$5:$H$19,"Blocked")+COUNTIF('Pending API Checks'!$H$5:$H$19,"BLOCKED") -> 0 | J5: =COUNTIF('Payments Received API'!$H$5:$H$23,"Need to Discuss")+COUNTIF('Expenses API'!$H$5:$H$14,"Need to Discuss")+COUNTIF('Pending API Checks'!$H$5:$H$19,"Need to Discuss")+COUNTIF('Payments Received API'!$H$5:$H$23,"FAIL")+COUNTIF('Expenses API'!$H$5:$H$14,"FAIL")+COUNTIF('Pending API Checks'!$H$5:$H$19,"FAIL") -> 0 | L5: =COUNTIF('Payments Received API'!$H$5:$H$23,"Pending")+COUNTIF('Payments Received API'!$H$5:$H$23,"PENDING")+COUNTIF('Expenses API'!$H$5:$H$14,"Pending")+COUNTIF('Expenses API'!$H$5:$H$14,"PENDING")+COUNTIF('Pending API Checks'!$H$5:$H$19,"Pending")+COUNTIF('Pending API Checks'!$H$5:$H$19,"PENDING") -> 28
B7: Status Breakdown | G7: API Suite Breakdown (Live Rollup)
B8: Status | C8: Tasks | D8: % of Tasks | E8: Completed Qty | G8: API Suite / Module | H8: Total Checks | I8: Completed | J8: Pending | K8: Blocked | L8: % Done | M8: Suite Status
B9: Completed | C9: =COUNTIF('Payments Received API'!$H$5:$H$23,"Completed")+COUNTIF('Payments Received API'!$H$5:$H$23,"PASS")+COUNTIF('Expenses API'!$H$5:$H$14,"Completed")+COUNTIF('Expenses API'!$H$5:$H$14,"PASS")+COUNTIF('Pending API Checks'!$H$5:$H$19,"Completed")+COUNTIF('Pending API Checks'!$H$5:$H$19,"PASS") -> 30 | D9: =IFERROR(C9/$B$5,0) -> 0.68181818 | E9: =IF(B9="Completed",C9,0) -> 30 | G9: Payments Received API | H9: =COUNTA('Payments Received API'!$A$5:$A$23) -> 19 | I9: =COUNTIF('Payments Received API'!$H$5:$H$23,"Completed")+COUNTIF('Payments Received API'!$H$5:$H$23,"PASS") -> 19 | J9: =COUNTIF('Payments Received API'!$H$5:$H$23,"Pending")+COUNTIF('Payments Received API'!$H$5:$H$23,"PENDING") -> 0 | K9: =COUNTIF('Payments Received API'!$H$5:$H$23,"Blocked")+COUNTIF('Payments Received API'!$H$5:$H$23,"BLOCKED")+COUNTIF('Payments Received API'!$H$5:$H$23,"FAIL") -> 0 | L9: =IFERROR(I9/H9,0) -> 1 | M9: =IF(I9=H9,"Completed",IF(K9>0,"Blocked",IF(I9>0,"In Progress","Pending"))) -> Completed
B10: In Progress | C10: =COUNTIF('Payments Received API'!$H$5:$H$23,"In Progress")+COUNTIF('Expenses API'!$H$5:$H$14,"In Progress")+COUNTIF('Pending API Checks'!$H$5:$H$19,"In Progress") -> 0 | D10: =IFERROR(C10/$B$5,0) -> 0 | E10: =IF(B10="Completed",C10,0) -> 0 | G10: Expenses API | H10: =COUNTA('Expenses API'!$A$5:$A$14) -> 10 | I10: =COUNTIF('Expenses API'!$H$5:$H$14,"Completed")+COUNTIF('Expenses API'!$H$5:$H$14,"PASS") -> 10 | J10: =COUNTIF('Expenses API'!$H$5:$H$14,"Pending")+COUNTIF('Expenses API'!$H$5:$H$14,"PENDING") -> 0 | K10: =COUNTIF('Expenses API'!$H$5:$H$14,"Blocked")+COUNTIF('Expenses API'!$H$5:$H$14,"BLOCKED")+COUNTIF('Expenses API'!$H$5:$H$14,"FAIL") -> 0 | L10: =IFERROR(I10/H10,0) -> 1 | M10: =IF(I10=H10,"Completed",IF(K10>0,"Blocked",IF(I10>0,"In Progress","Pending"))) -> Completed
B11: In Review | C11: =COUNTIF('Payments Received API'!$H$5:$H$23,"In Review")+COUNTIF('Expenses API'!$H$5:$H$14,"In Review")+COUNTIF('Pending API Checks'!$H$5:$H$19,"In Review") -> 0 | D11: =IFERROR(C11/$B$5,0) -> 0 | E11: =IF(B11="Completed",C11,0) -> 0 | G11: Pending API Checks | H11: =COUNTA('Pending API Checks'!$A$5:$A$19) -> 15 | I11: =COUNTIF('Pending API Checks'!$H$5:$H$19,"Completed")+COUNTIF('Pending API Checks'!$H$5:$H$19,"PASS") -> 1 | J11: =COUNTIF('Pending API Checks'!$H$5:$H$19,"Pending")+COUNTIF('Pending API Checks'!$H$5:$H$19,"PENDING") -> 28 | K11: =COUNTIF('Pending API Checks'!$H$5:$H$19,"Blocked")+COUNTIF('Pending API Checks'!$H$5:$H$19,"BLOCKED")+COUNTIF('Pending API Checks'!$H$5:$H$19,"FAIL") -> 0 | L11: =IFERROR(I11/H11,0) -> 0.066666667 | M11: =IF(I11=H11,"Completed",IF(K11>0,"Blocked",IF(I11>0,"In Progress","Pending"))) -> In Progress
B12: Pending | C12: =COUNTIF('Payments Received API'!$H$5:$H$23,"Pending")+COUNTIF('Payments Received API'!$H$5:$H$23,"PENDING")+COUNTIF('Expenses API'!$H$5:$H$14,"Pending")+COUNTIF('Expenses API'!$H$5:$H$14,"PENDING")+COUNTIF('Pending API Checks'!$H$5:$H$19,"Pending")+COUNTIF('Pending API Checks'!$H$5:$H$19,"PENDING") -> 28 | D12: =IFERROR(C12/$B$5,0) -> 0.63636364 | E12: =IF(B12="Completed",C12,0) -> 0 | G12: Total All Suites | H12: =SUM(H9:H11) -> 44 | I12: =SUM(I9:I11) -> 30 | J12: =SUM(J9:J11) -> 28 | K12: =SUM(K9:K11) -> 0 | L12: =IFERROR(I12/H12,0) -> 0.68181818 | M12: =IF(I12=H12,"Completed",IF(K12>0,"Blocked",IF(I12>0,"In Progress","Pending"))) -> In Progress
B13: Blocked | C13: =COUNTIF('Payments Received API'!$H$5:$H$23,"Blocked")+COUNTIF('Payments Received API'!$H$5:$H$23,"BLOCKED")+COUNTIF('Expenses API'!$H$5:$H$14,"Blocked")+COUNTIF('Expenses API'!$H$5:$H$14,"BLOCKED")+COUNTIF('Pending API Checks'!$H$5:$H$19,"Blocked")+COUNTIF('Pending API Checks'!$H$5:$H$19,"BLOCKED") -> 0 | D13: =IFERROR(C13/$B$5,0) -> 0 | E13: =IF(B13="Completed",C13,0) -> 0
B14: Need to Discuss | C14: =COUNTIF('Payments Received API'!$H$5:$H$23,"Need to Discuss")+COUNTIF('Expenses API'!$H$5:$H$14,"Need to Discuss")+COUNTIF('Pending API Checks'!$H$5:$H$19,"Need to Discuss")+COUNTIF('Payments Received API'!$H$5:$H$23,"FAIL")+COUNTIF('Expenses API'!$H$5:$H$14,"FAIL")+COUNTIF('Pending API Checks'!$H$5:$H$19,"FAIL") -> 0 | D14: =IFERROR(C14/$B$5,0) -> 0 | E14: =IF(B14="Completed",C14,0) -> 0
B15: Not Started | C15: =COUNTIF('Payments Received API'!$H$5:$H$23,"Not Started")+COUNTIF('Expenses API'!$H$5:$H$14,"Not Started")+COUNTIF('Pending API Checks'!$H$5:$H$19,"Not Started") -> 0 | D15: =IFERROR(C15/$B$5,0) -> 0 | E15: =IF(B15="Completed",C15,0) -> 0
B16: Total | C16: =SUM(C9:C15) -> 58 | D16: =SUM(D9:D15) -> 1.3181818 | E16: =SUM(E9:E15) -> 30

Sheet Payments Received API
A1: TexaWave ERP - Payments Received API Tracker (Postman Manual Test Cases)
A2: Do not edit the navy columns (API test spec). Update Status ('Completed' button), % Done, Actual Result / Notes, and Last Updated. Dashboard updates automatically.
A4: Test ID | B4: Test Method | C4: URL | D4: JSON Code for Test | E4: Expected Result | F4: Explanation / Steps to Do | G4: Prerequisites / Variables | H4: Status | I4: % Done | J4: Actual Result / Notes | K4: Last Updated
A5: PR-001 | B5: POST | C5: {{baseUrl}}/auth/login | D5: { "organizationSlug": "{{organizationSlug}}", "email": "{{email}}", "password": "{{password}}" } | E5: Expected per project guide: 201 Created; response contains data.accessToken. | F5: Set Body → raw → JSON, enter your real local credentials, click Send, save data.accessToken as accessToken. Check current auth controller if status differs. | G5: baseUrl, organizationSlug, email, password | H5: Completed | I5: =IF(OR(H5="Completed",H5="PASS"),1,IF(OR(H5="In Progress",H5="In Review"),0.5,0)) -> 1 | J5: 201 OK (121 MS)
A6: PR-002 | B6: GET | C6: {{baseUrl}}/finance-settings/master-list-items?category=payment_mode&limit=10 | D6: (No body) | E6: 200 OK with payment mode items; save a real item id as paymentModeId. | F6: Add Bearer token. Click Send. Pick an active payment mode from the response; do not guess its ID. | G6: accessToken; finance settings read permission | H6: Completed | I6: =IF(OR(H6="Completed",H6="PASS"),1,IF(OR(H6="In Progress",H6="In Review"),0.5,0)) -> 1 | J6: 200 OK (46MS)
A7: PR-003 | B7: GET | C7: {{baseUrl}}/finance/bank-accounts | D7: { "invoiceReference": "TEST-INV-TOO+D21 | E7: Expected 200 OK if route and permission are enabled; save an eligible bankAccountId. | F7: Send with Bearer token. If no account exists, mark BLOCKED and ask for a test account to be seeded. | G7: accessToken; check current controller/permission | H7: Completed | I7: =IF(OR(H7="Completed",H7="PASS"),1,IF(OR(H7="In Progress",H7="In Review"),0.5,0)) -> 1 | J7: 200 OK (26 MS)
A8: PR-004 | B8: GET | C8: {{baseUrl}}/crm/accounts?type=CUSTOMER | D8: (No body) | E8: Expected 200 OK if this route/query matches the current CRM API; save a real customerId. | F8: Send with Bearer token. If route differs, inspect current CRM controller and update URL; do not guess IDs. | G8: accessToken; CRM read permission | H8: Completed | I8: =IF(OR(H8="Completed",H8="PASS"),1,IF(OR(H8="In Progress",H8="In Review"),0.5,0)) -> 1 | J8: 200 OK (23 MS)
A9: PR-005 | B9: POST | C9: {{baseUrl}}/finance/payments-received | D9: { "paymentDate": "2026-10-23", "amount": 8000.00, "paymentModeId": {{paymentModeId}}, "customerName": "Globex Corporation", "referenceNumber": "TEST-NEFT-001", "notes": "Postman test - customer advance", "status": "DRAFT", "allocations": [ {"invoiceReference": "TEST-INV-0044", "allocatedAmount": 3000.00, "notes": "Test partial allocation"}, {"invoiceReference": "TEST-INV-0045", "allocatedAmount": 2000.00, "notes": "Test second allocation"} ] } | E9: Expected 201 Created per guide. amount=8000, allocatedAmount=5000, unallocatedAmount=3000, status=DRAFT. Save data.id as paymentReceivedId and first allocation id as allocationId. | F9: Use test data. Important: current DTO may require customerId instead of customerName and may require bankAccountId. Check current DTO; adapt body accordingly before sending. | G9: accessToken, paymentModeId; customerId/bankAccountId if required | H9: Completed | I9: =IF(OR(H9="Completed",H9="PASS"),1,IF(OR(H9="In Progress",H9="In Review"),0.5,0)) -> 1 | J9: 200 OK (26 MS), paymentmodeid 7, payment recive id : (7) 14
A10: PR-006 | B10: GET | C10: {{baseUrl}}/finance/payments-received/{{paymentReceivedId}} | D10: (No body) | E10: 200 OK; id matches and details/allocations persist. | F10: Run after create succeeds. Compare amount, status, allocation rows and totals. | G10: paymentReceivedId; read permission | H10: Completed | I10: =IF(OR(H10="Completed",H10="PASS"),1,IF(OR(H10="In Progress",H10="In Review"),0.5,0)) -> 1 | J10: 200 OK (129 MS)
A11: PR-007 | B11: GET | C11: {{baseUrl}}/finance/payments-received?page=1&limit=10&status=DRAFT | D11: (No body) | E11: 200 OK with paginated list and metadata; created draft should appear. | F11: Find the created receipt in the result and check pagination metadata. | G11: read permission | H11: Completed | I11: =IF(OR(H11="Completed",H11="PASS"),1,IF(OR(H11="In Progress",H11="In Review"),0.5,0)) -> 1 | J11: 200 OK (61 MS)
A12: PR-008 | B12: PATCH | C12: {{baseUrl}}/finance/payments-received/{{paymentReceivedId}} | D12: { "referenceNumber": "TEST-NEFT-UPDATED-001", "notes": "Updated reference during Postman test" } | E12: Expected 200 OK; reference and notes updated, totals unchanged. | F12: Use a DRAFT test receipt. Send JSON, then GET the receipt again to verify persistence. | G12: paymentReceivedId; write permission | H12: Completed | I12: =IF(OR(H12="Completed",H12="PASS"),1,IF(OR(H12="In Progress",H12="In Review"),0.5,0)) -> 1 | J12: 200 OK (11 MS)
A13: PR-009 | B13: POST | C13: {{baseUrl}}/finance/payments-received/{{paymentReceivedId}}/allocations | D13: { "invoiceReference": "TEST-INV-0046", "allocatedAmount": 500.00, "notes": "Additional allocation test" } | E13: Expected 201 per guide. If initial allocation was 5000, allocatedAmount=5500 and unallocatedAmount=2500. | F13: Ensure at least 500 remains unallocated. Send; record actual response shape because audit reported frontend/backend return-type mismatch. | G13: paymentReceivedId; write permission; enough unallocated amount | H13: Completed | I13: =IF(OR(H13="Completed",H13="PASS"),1,IF(OR(H13="In Progress",H13="In Review"),0.5,0)) -> 1 | J13: 201 OK (41 MS)
A14: PR-010 | B14: DELETE | C14: {{baseUrl}}/finance/payments-received/{{paymentReceivedId}}/allocations/{{allocationId}} | D14: (No body) | E14: Expected 204 No Content; allocation removed and unallocated balance increases by its amount. | F14: Use allocationId from create response. Then GET receipt and check totals. Test record only. | G14: paymentReceivedId, allocationId; write permission | H14: Completed | I14: =IF(OR(H14="Completed",H14="PASS"),1,IF(OR(H14="In Progress",H14="In Review"),0.5,0)) -> 1 | J14: 204 NO CONTENT (18 MS)
A15: PR-011 | B15: POST | C15: {{baseUrl}}/finance/payments-received/{{paymentReceivedId}}/confirm | D15: {} | E15: Expected per guide: 201 Created, status=CONFIRMED, journalEntryId exists; journal debits equal credits. | F15: Only use a dedicated test receipt in a safe dev DB. Send {}. Inspect journal details if exposed. Never do this on production data. | G15: paymentReceivedId; write permission; safe test DB | H15: Completed | I15: =IF(OR(H15="Completed",H15="PASS"),1,IF(OR(H15="In Progress",H15="In Review"),0.5,0)) -> 1 | J15: 201 Created (15 MS)
A16: PR-012 | B16: POST | C16: {{baseUrl}}/finance/payments-received/{{paymentReceivedId}}/confirm | D16: {} | E16: Expected 422 or documented conflict; second confirmation must not create a duplicate journal. | F16: Run only after test receipt was confirmed. Send again and verify rejection/no duplicate journal. | G16: Already-confirmed test receipt | H16: Completed | I16: =IF(OR(H16="Completed",H16="PASS"),1,IF(OR(H16="In Progress",H16="In Review"),0.5,0)) -> 1 | J16: EXPECTED 422 ALREDY CREATED (11 MS)
... A23: PR-019 | B23: PATCH | C23: {{baseUrl}}/finance/payments-received/{{paymentReceivedId}} | D23: { "referenceNumber": "SHOULD-NOT-UPDATE", "notes": "Attempt to edit void receipt" } | E23: Expected documented rejection (audit suggests 422) for immutable VOID receipt. | F23: Run only with a VOID test receipt. Send and verify record remains unchanged. | G23: VOID test receipt; write permission | H23: Completed | I23: =IF(OR(H23="Completed",H23="PASS"),1,IF(OR(H23="In Progress",H23="In Review"),0.5,0)) -> 1 | J23: EXPECTED

Sheet Expenses API
A1: TexaWave ERP - Expenses API Tracker (Lifecycle: DRAFT → SUBMIT → APPROVE → PAY → CANCEL)
A2: Do not edit the navy columns (API test spec). Update Status ('Completed' button), % Done, Actual Result / Notes, and Last Updated. Dashboard updates automatically.
A4: Test ID | B4: Test Method | C4: URL | D4: JSON Code for Test | E4: Expected Result | F4: Explanation / Steps to Do | G4: Prerequisites / Variables | H4: Status | I4: % Done | J4: Actual Result / Notes | K4: Last Updated
A5: EXP-001 | B5: POST | C5: {{baseUrl}}/finance/expenses | D5: { "expenseTypeId": {{expenseTypeId}}, "expenseDate": "2026-10-23", "amount": 3000.00, "taxAmount": 540.00, "paymentModeId": {{paymentModeId}}, "vendorName": "Apex Office Hub", "referenceNumber": "TEST-EXP-001", "notes": "Postman test - workstation equipment", "status": "DRAFT" } | E5: Expected 201; status=DRAFT; netAmount may equal 3540 if net is amount plus tax. Save data.id as expenseId. | F5: Discover expenseTypeId and paymentModeId first. Send as raw JSON; check current DTO for required fields. | G5: expenseTypeId, paymentModeId; write permission | H5: Completed | I5: =IF(OR(H5="Completed",H5="PASS"),1,IF(OR(H5="In Progress",H5="In Review"),0.5,0)) -> 1 | J5: expected 201
A6: EXP-002 | B6: GET | C6: {{baseUrl}}/finance/expenses/{{expenseId}} | D6: (No body) | E6: 200 OK; expense detail returned with status DRAFT. | F6: Run after create; verify id, amount, status and fields. | G6: expenseId; read permission | H6: Completed | I6: =IF(OR(H6="Completed",H6="PASS"),1,IF(OR(H6="In Progress",H6="In Review"),0.5,0)) -> 1 | J6: 200 OK
A7: EXP-003 | B7: GET | C7: {{baseUrl}}/finance/expenses?status=DRAFT&page=1&limit=10 | D7: (No body) | E7: 200 OK; list includes the draft and pagination metadata. | F7: Find expense by ID in result. | G7: read permission | H7: Completed | I7: =IF(OR(H7="Completed",H7="PASS"),1,IF(OR(H7="In Progress",H7="In Review"),0.5,0)) -> 1 | J7: 200 OK
A8: EXP-004 | B8: PATCH | C8: {{baseUrl}}/finance/expenses/{{expenseId}} | D8: { "amount": 3200.00, "taxAmount": 576.00, "notes": "Updated test amount" } | E8: Expected 200; netAmount may equal 3776 if the current rule is amount + tax. | F8: Update only a DRAFT test expense. GET it again to verify. | G8: expenseId; write permission | H8: Completed | I8: =IF(OR(H8="Completed",H8="PASS"),1,IF(OR(H8="In Progress",H8="In Review"),0.5,0)) -> 1 | J8: 200 OK
A9: EXP-005 | B9: POST | C9: {{baseUrl}}/finance/expenses/{{expenseId}}/submit | D9: {} | E9: Expected 201 per guide; status=PENDING_APPROVAL. | F9: Run after draft is created; verify response/GET. | G9: expenseId; write permission | H9: Completed | I9: =IF(OR(H9="Completed",H9="PASS"),1,IF(OR(H9="In Progress",H9="In Review"),0.5,0)) -> 1 | J9: 201 created
A10: EXP-006 | B10: POST | C10: {{baseUrl}}/finance/expenses/{{expenseId}}/approve | D10: {} | E10: Expected 201 per guide; status=APPROVED. | F10: Run only after submission; use an authorized test role. | G10: expenseId; approval permission | H10: Completed | I10: =IF(OR(H10="Completed",H10="PASS"),1,IF(OR(H10="In Progress",H10="In Review"),0.5,0)) -> 1 | J10: 201 created
A11: EXP-007 | B11: POST | C11: {{baseUrl}}/finance/expenses/{{expenseId}}/pay | D11: { "paymentDate": "2026-10-23", "referenceNumber": "TEST-NEFT-EXP-001" } | E11: Expected 201 per guide; status=PAID, journalEntryId exists and journal is balanced. | F11: Only on an APPROVED test expense in safe dev DB. Inspect journal details. | G11: expenseId; APPROVED test expense | H11: Completed | I11: =IF(OR(H11="Completed",H11="PASS"),1,IF(OR(H11="In Progress",H11="In Review"),0.5,0)) -> 1 | J11: Exxpected 201
A12: EXP-008 | B12: POST | C12: {{baseUrl}}/finance/expenses/{{expenseId}}/cancel | D12: {} | E12: Expected 201 per guide; status=CANCELLED and reversal journal exists. | F12: Only after successful test payment. Verify reversal journal balances. | G12: PAID test expense | H12: Completed | I12: =IF(OR(H12="Completed",H12="PASS"),1,IF(OR(H12="In Progress",H12="In Review"),0.5,0)) -> 1 | J12: 201 created
A13: EXP-009 | B13: DELETE | C13: {{baseUrl}}/finance/expenses/{{expenseId}} | D13: (No body) | E13: Expected 204; soft-delete permitted after cancellation. | F13: Only on cancelled test expense. Verify list/detail behavior. | G13: CANCELLED test expense | H13: Completed | I13: =IF(OR(H13="Completed",H13="PASS"),1,IF(OR(H13="In Progress",H13="In Review"),0.5,0)) -> 1 | J13: 204 No Content
A14: EXP-010 | B14: POST | C14: {{baseUrl}}/finance/expenses | D14: { "expenseTypeId": {{expenseTypeId}}, "expenseDate": "2099-01-01", "amount": 1000, "taxAmount": 0, "paymentModeId": {{paymentModeId}}, "vendorName": "Future Date Negative Test", "referenceNumber": "TEST-EXP-FUTURE", "notes": "Intentional invalid future date", "status": "DRAFT" } | E14: Expected 422 FUTURE_EXPENSE_DATE or equivalent; no record created. | F14: Separate negative test; verify no record was created. Adapt body to current DTO. | G14: expenseTypeId, paymentModeId; write permission | H14: Completed | I14: =IF(OR(H14="Completed",H14="PASS"),1,IF(OR(H14="In Progress",H14="In Review"),0.5,0)) -> 1 | J14: 422 Expected

Sheet Pending API Checks
A1: TexaWave ERP - Pending API & Security Verification Tracker (Audit & Risk Backlog)
A2: Do not edit the navy columns (Verification spec). Update Status ('Completed' button), % Done, Evidence / Notes, and Last Updated. Dashboard updates automatically.
A4: Check ID | B4: Area | C4: API / Check | D4: Why Pending / Risk | E4: How to Verify | F4: Expected Result / Acceptance Criteria | G4: Priority | H4: Status | I4: % Done | J4: Evidence / Notes | K4: Last Updated
A5: CHK-001 | B5: Payments Received | C5: Create → GET → list | D5: Prepared guide does not prove live requests were executed. | E5: Run create, detail and list rows; save sanitized responses. | F5: Created receipt persists and appears in detail/list. | G5: P1 | H5: PASS | I5: =IF(OR(H5="Completed",H5="PASS"),1,IF(OR(H5="In Progress",H5="In Review"),0.5,0)) -> 1
A6: CHK-002 | B6: Payments Received | C6: Confirm + GL posting | D6: Live database posting not proven by unit tests alone. | E6: Confirm a test receipt and inspect journal detail. | F6: CONFIRMED; one journal only; total debits = total credits. | G6: P1 | H6: Pending | I6: =IF(OR(H6="Completed",H6="PASS"),1,IF(OR(H6="In Progress",H6="In Review"),0.5,0)) -> 0
A7: CHK-003 | B7: Payments Received | C7: Void + reversal | D7: Live reversal still needs manual verification. | E7: Void a confirmed test receipt and inspect original/reversal journals. | F7: VOID; original journal reversed; reversal balances. | G7: P1 | H7: Pending | I7: =IF(OR(H7="Completed",H7="PASS"),1,IF(OR(H7="In Progress",H7="In Review"),0.5,0)) -> 0
A8: CHK-004 | B8: Payments Received | C8: Allocation arithmetic | D8: Need to verify persisted totals after add/remove. | E8: GET receipt after every allocation change. | F8: allocatedAmount equals allocation sum; unallocatedAmount equals amount minus allocated. | G8: P1 | H8: Pending | I8: =IF(OR(H8="Completed",H8="PASS"),1,IF(OR(H8="In Progress",H8="In Review"),0.5,0)) -> 0
A9: CHK-005 | B9: Payments Received | C9: Overdue/due-month filters | D9: Audit found client-side filtering of only current page and no authoritative SalesInvoice model. | E9: Inspect DTO/repository; test with more than 15 records if possible. | F9: No advance credit labelled overdue; accurate server-side counts or unsupported filter disabled. | G9: P0 | H9: Pending | I9: =IF(OR(H9="Completed",H9="PASS"),1,IF(OR(H9="In Progress",H9="In Review"),0.5,0)) -> 0
A10: CHK-006 | B10: Payments Received | C10: Invoice source and status synchronization | D10: Invoice reference is free text; project guide says no dedicated SalesInvoice model. | E10: Inspect schema and Sales integration; document dependency. | F10: Do not claim live invoice balance, due date or payment-status sync without authoritative source. | G10: P1 | H10: Pending | I10: =IF(OR(H10="Completed",H10="PASS"),1,IF(OR(H10="In Progress",H10="In Review"),0.5,0)) -> 0
A11: CHK-007 | B11: Payments Received UI | C11: Edit draft action | D11: Audit reports PATCH exists but UI edit action is missing. | E11: After implementation, edit DRAFT in UI then GET via API. | F11: Draft can be edited; confirmed/reconciled/void remain restricted. | G11: P2 | H11: Pending | I11: =IF(OR(H11="Completed",H11="PASS"),1,IF(OR(H11="In Progress",H11="In Review"),0.5,0)) -> 0
A12: CHK-008 | B12: Payments Received API | C12: Allocation response typing | D12: Audit reports frontend type differs from backend response. | E12: Compare controller/service response with api.ts and run allocation request. | F12: Frontend type matches actual backend payload. | G12: P2 | H12: Pending | I12: =IF(OR(H12="Completed",H12="PASS"),1,IF(OR(H12="In Progress",H12="In Review"),0.5,0)) -> 0
A13: CHK-009 | B13: Security | C13: Unauthenticated request | D13: Needs live security check. | E13: Send protected GET without Authorization. | F13: 401; no protected data returned. | G13: P1 | H13: Pending | I13: =IF(OR(H13="Completed",H13="PASS"),1,IF(OR(H13="In Progress",H13="In Review"),0.5,0)) -> 0
A14: CHK-010 | B14: Security | C14: Write permission denial | D14: Requires a read-only test account. | E14: POST using token without write permission. | F14: 403; no record created. | G14: P1 | H14: Pending | I14: =IF(OR(H14="Completed",H14="PASS"),1,IF(OR(H14="In Progress",H14="In Review"),0.5,0)) -> 0
A15: CHK-011 | B15: Security | C15: Tenant isolation | D15: Requires two test organizations. | E15: Try Org A's record ID using Org B token. | F15: No cross-tenant data leakage; project contract expects 404. | G15: P1 | H15: Pending | I15: =IF(OR(H15="Completed",H15="PASS"),1,IF(OR(H15="In Progress",H15="In Review"),0.5,0)) -> 0
A16: CHK-012 | B16: Expenses | C16: Draft → submit → approve → pay → cancel | D16: Prepared manual tests need live execution. | E16: Run lifecycle on a test-only expense. | F16: Correct states and balanced posting/reversal entries. | G16: P1 | H16: Pending | I16: =IF(OR(H16="Completed",H16="PASS"),1,IF(OR(H16="In Progress",H16="In Review"),0.5,0)) -> 0
... A19: CHK-015 | B19: Request contract | C19: Customer and bank prerequisites | D19: Docs vary between customerName/customerId and optional/required bankAccountId. | E19: Compare current DTO and controller; run discovery requests. | F19: Requests use actual required fields and real IDs. | G19: P1 | H19: Pending | I19: =IF(OR(H19="Completed",H19="PASS"),1,IF(OR(H19="In Progress",H19="In Review"),0.5,0)) -> 0

Sheet How to Update
B1: How to Update the Finance API Test Tracker
B3: 1. Open 'Payments Received API', 'Expenses API', or 'Pending API Checks' and pick the test case row you are executing.
B4: 2. Click the Status pill button in Column H and select 'Completed' once the Postman request passes all Expected Result checks.
B5: 3. Use 'Blocked' or 'Need to Discuss' (or 'FAIL') immediately if a route, DTO contract, or database prerequisite fails — do not wait.
B6: 4. Always record sanitized response evidence or error details in Column J ('Actual Result / Notes') and put today's date in Column K ('Last Updated' — Ctrl + ;).
B7: 5. Do not edit the navy columns (Columns A–G test specification data). The Dashboard and % Done counters update automatically.
B8: Example: Status = Completed | % Done = 100% | Actual Result = '201 Created; paymentReceivedId saved; journalEntryId balanced'
B10: Status Button | C10: When to use it
B11: Completed | C11: Request executed in Postman and actual HTTP status, payload, and DB persistence match Expected Result.
B12: In Progress | C12: Currently configuring prerequisites, tokens, or actively testing the endpoint.
B13: In Review | C13: Endpoint tested; response or DTO mismatch raised for PR/backend review.
B14: Pending | C14: Default initial state — manual verification has not been executed yet.
B15: Blocked | C15: Cannot execute due to missing seed data, unavailable test DB/Redis, or missing route/permission.
B16: Need to Discuss | C16: Contract caveat or unexpected 422/500 behavior that requires team discussion.
B17: Not Started | C17: Test suite scheduled for a later sprint phase.
B19: Postman Runbook Topic | C19: Operational Instructions (from Original Workbook)
B20: Purpose | C20: Manual API test cases for Finance Operations while UI implementation continues. All test statuses start as PENDING; mark PASS only after executing the request.
B21: Safety | C21: Use only local development/test data. Never run confirm, void, cancel, or delete requests against production or real financial records.
B22: Setup | C22: Start the API using the repository's normal command. Use the actual API port from the terminal; do not assume the example port is correct.
... B31: E2E caveat | C31: Project notes say the E2E harness was blocked because a disposable test database and dedicated Redis were unavailable. These manual checks remain pending until executed safely.

Sheet Project Info
B1: Project Info — TexaWave ERP Finance API Verification
B3: Metric | C3: Value | D3: Notes
B4: Workbook Name | C4: TexaWave ERP — Finance Postman API Test Tracker | D4: Redesigned to match TexaWave_ERP_Sprint_Plan_Revised architecture
B5: Target Environment | C5: Local Development API + Disposable Test DB | D5: Never run confirm, void, cancel, or delete against production records
B6: Payments Received Tests | C6: 19 Manual API Test Cases (PR-001 to PR-019) | D6: Covers Auth, Discovery, Create, Allocate, Confirm, Void, Delete & Negative 422s
B7: Expenses API Tests | C7: 10 Manual API Test Cases (EXP-001 to EXP-010) | D7: Covers Draft, GET, PATCH, Submit, Approve, Pay, Cancel, Delete & Future Date 422
B8: Pending API & Security Checks | C8: 15 Audit & Risk Checks (CHK-001 to CHK-015) | D8: Covers GL posting, reversal, RBAC 401/403, tenant isolation 404, and E2E guard
B9: Total Verification Items | C9: =Dashboard!B5 -> 44 | D9: Automatically summed across all 3 tracker sheets
B10: Contract Caveat | C10: customerName vs customerId & bankAccountId | D10: Verify current DTO/controller before sending create requests
B11: Invoice Caveat | C11: No dedicated SalesInvoice Prisma model | D11: Invoice references are free-text strings; do not claim live invoice sync
