Workbook

Sheet Cover
A1: TEXAWAVE ERP — FINANCE MODULE TEST PLAN & RESULTS
A2: Purpose | B2: Track automated tests, Postman API tests, manual UI walkthroughs, database/accounting validation, E2E, security, regression, and bugs.
A4: How to use
A5: Rule 1 | B5: 1. Run tests only in the approved local/test environment. Do not post/delete/deactivate real production financial data.
A6: Rule 2 | B6: 2. Start with the project's existing Postman collection/environment. Do not invent endpoints or payloads; record real request names and results.
A7: Rule 3 | B7: 3. Status values: NOT RUN, PASS, FAIL, BLOCKED, NOT APPLICABLE. Never mark a test PASS until it has actually been executed and verified.
A8: Rule 4 | B8: 4. For manual UI tests, enter actual result, screenshot/evidence path, date, and issue ID.
A9: Rule 5 | B9: 5. For automated tests, record the exact command, actual pass/fail counts, and report/log path.
A10: Rule 6 | B10: 6. Keep API, unit, integration, E2E, and manual UI results separate. Unit tests alone do not prove the live API/database flow works.
A11: Rule 7 | B11: 7. After a code/test change, update the relevant test row and Summary. Preserve all existing local code and test data.
A12: Rule 8 | B12: 8. Journal vouchers must remain balanced (total debit = total credit); never weaken backend validation.
A13: Rule 9 | B13: 9. This workbook is a tracking template. Antigravity must inspect the repository and populate exact routes, scripts, and actual results.
A15: Initial status | B15: Automated baseline executed; Manual UI cases preserved as NOT RUN for walkthrough.
A17: Important | B17: Do not claim tests passed without command output, Postman response evidence, or a manual observation.

Sheet Summary
A1: FINANCE TEST EXECUTION SUMMARY
A2: Live status summary calculated dynamically from each category sheet
A3: Test category | B3: Total cases | C3: PASS | D3: FAIL | E3: BLOCKED | F3: NOT RUN
A4: Manual UI | B4: =COUNTA('Manual UI'!$H$4:$H$26) -> 23 | C4: =COUNTIF('Manual UI'!$H$4:$H$26, "PASS") -> 0 | D4: =COUNTIF('Manual UI'!$H$4:$H$26, "FAIL") -> 0 | E4: =COUNTIF('Manual UI'!$H$4:$H$26, "BLOCKED") -> 0 | F4: =COUNTIF('Manual UI'!$H$4:$H$26, "NOT RUN") -> 23
A5: Postman API | B5: =COUNTA('Postman API'!$H$4:$H$17) -> 14 | C5: =COUNTIF('Postman API'!$H$4:$H$17, "PASS") -> 0 | D5: =COUNTIF('Postman API'!$H$4:$H$17, "FAIL") -> 0 | E5: =COUNTIF('Postman API'!$H$4:$H$17, "BLOCKED") -> 14 | F5: =COUNTIF('Postman API'!$H$4:$H$17, "NOT RUN") -> 0
A6: Unit Tests | B6: =COUNTA('Unit Tests'!$H$4:$H$11) -> 8 | C6: =COUNTIF('Unit Tests'!$H$4:$H$11, "PASS") -> 8 | D6: =COUNTIF('Unit Tests'!$H$4:$H$11, "FAIL") -> 0 | E6: =COUNTIF('Unit Tests'!$H$4:$H$11, "BLOCKED") -> 0 | F6: =COUNTIF('Unit Tests'!$H$4:$H$11, "NOT RUN") -> 0
A7: Integration | B7: =COUNTA('Integration'!$H$4:$H$11) -> 8 | C7: =COUNTIF('Integration'!$H$4:$H$11, "PASS") -> 7 | D7: =COUNTIF('Integration'!$H$4:$H$11, "FAIL") -> 0 | E7: =COUNTIF('Integration'!$H$4:$H$11, "BLOCKED") -> 1 | F7: =COUNTIF('Integration'!$H$4:$H$11, "NOT RUN") -> 0
A8: E2E Tests | B8: =COUNTA('E2E Tests'!$H$4:$H$9) -> 6 | C8: =COUNTIF('E2E Tests'!$H$4:$H$9, "PASS") -> 5 | D8: =COUNTIF('E2E Tests'!$H$4:$H$9, "FAIL") -> 0 | E8: =COUNTIF('E2E Tests'!$H$4:$H$9, "BLOCKED") -> 0 | F8: =COUNTIF('E2E Tests'!$H$4:$H$9, "NOT RUN") -> 1
A9: Database Checks | B9: =COUNTA('Database Checks'!$H$4:$H$9) -> 6 | C9: =COUNTIF('Database Checks'!$H$4:$H$9, "PASS") -> 6 | D9: =COUNTIF('Database Checks'!$H$4:$H$9, "FAIL") -> 0 | E9: =COUNTIF('Database Checks'!$H$4:$H$9, "BLOCKED") -> 0 | F9: =COUNTIF('Database Checks'!$H$4:$H$9, "NOT RUN") -> 0
A10: Security | B10: =COUNTA('Security'!$H$4:$H$8) -> 5 | C10: =COUNTIF('Security'!$H$4:$H$8, "PASS") -> 5 | D10: =COUNTIF('Security'!$H$4:$H$8, "FAIL") -> 0 | E10: =COUNTIF('Security'!$H$4:$H$8, "BLOCKED") -> 0 | F10: =COUNTIF('Security'!$H$4:$H$8, "NOT RUN") -> 0
A11: Regression | B11: =COUNTA('Regression'!$H$4:$H$10) -> 7 | C11: =COUNTIF('Regression'!$H$4:$H$10, "PASS") -> 7 | D11: =COUNTIF('Regression'!$H$4:$H$10, "FAIL") -> 0 | E11: =COUNTIF('Regression'!$H$4:$H$10, "BLOCKED") -> 0 | F11: =COUNTIF('Regression'!$H$4:$H$10, "NOT RUN") -> 0
A12: Total | B12: =SUM(B4:B11) -> 77 | C12: =SUM(C4:C11) -> 38 | D12: =SUM(D4:D11) -> 0 | E12: =SUM(E4:E11) -> 15 | F12: =SUM(F4:F11) -> 24
A14: Important | B14: Counts update automatically from each sheet's Status column. Tests remain NOT RUN until actually executed.

Sheet Manual UI
A1: FINANCE MANUAL UI TEST CASES
A2: TexaOne ERP Quality Assurance — Manual UI Tracking
A3: Test ID | B3: Area / Feature | C3: Test case | D3: Preconditions / Test data | E3: Steps / Command | F3: Expected result | G3: Actual result / Evidence | H3: Status | I3: Priority | J3: Issue ID | K3: Executed by | L3: Execution date
A4: UI-COA-001 | B4: Chart of Accounts | C4: Initial load and refresh | D4: Authorized test user | E4: Open Finance → Accounting → Chart of Accounts; refresh | F4: Page loads and account data/columns display | H4: NOT RUN | I4: P1
A5: UI-COA-002 | B5: Chart of Accounts | C5: Search by code | D5: Known test account code | E5: Search known code (e.g. 1010 only if present); clear search | F5: Matching account appears; clearing restores list | H5: NOT RUN | I5: P1
A6: UI-COA-003 | B6: Chart of Accounts | C6: Search by name | D6: Known account name | E6: Search exact and partial name | F6: Expected matches appear | H6: NOT RUN | I6: P2
A7: UI-COA-004 | B7: Chart of Accounts | C7: Classification filter | D7: Accounts across available classifications | E7: Select each available classification | F7: Only matching accounts appear | H7: NOT RUN | I7: P1
A8: UI-COA-005 | B8: Chart of Accounts | C8: Status filter | D8: Existing active/inactive records if available | E8: Select each available status | F8: Results match filter | H8: NOT RUN | I8: P2
A9: UI-COA-006 | B9: Chart of Accounts | C9: Table/tree consistency | D9: Account with known parent | E9: Switch Table and Hierarchy Tree | F9: Records and parent relationships are consistent | H9: NOT RUN | I9: P1
A10: UI-COA-007 | B10: Chart of Accounts | C10: Create test account | D10: Approved test DB; unique code | E10: Create uniquely named QA account; reopen and refresh | F10: Account persists and fields are correct | H10: NOT RUN | I10: P1
A11: UI-COA-008 | B11: Chart of Accounts | C11: Required field validation | D11: Approved test DB | E11: Submit create form with required field missing | F11: Validation shown; no invalid record created | H11: NOT RUN | I11: P1
A12: UI-COA-009 | B12: Chart of Accounts | C12: Duplicate code validation | D12: Approved test DB; existing code | E12: Attempt duplicate account code | F12: Duplicate rejected according to actual uniqueness rule | H12: NOT RUN | I12: P1
A13: UI-COA-010 | B13: Chart of Accounts | C13: Parent relationship | D13: Approved test account | E13: Assign appropriate parent; verify table and tree | F13: Relationship persists and displays correctly | H13: NOT RUN | I13: P1
A14: UI-COA-011 | B14: Chart of Accounts | C14: Balance vs General Ledger | D14: Known account/date range | E14: Compare displayed balance with ledger calculation | F14: Balances agree under documented accounting rules | H14: NOT RUN | I14: P1
A15: UI-JV-001 | B15: Journal Voucher | C15: Balanced voucher | D15: Approved test DB; valid accounts | E15: Create voucher with equal debit/credit and submit | F15: One voucher posts; GL reflects it | H15: NOT RUN | I15: P1
... A26: UI-UX-001 | B26: Finance UX | C26: Page-by-page visual walkthrough | D26: Finance test environment | E26: Walk through each Finance page; capture unclear controls | F26: Findings recorded with screenshot/evidence | H26: NOT RUN | I26: P2

Sheet Postman API
A1: FINANCE POSTMAN API AUTOMATION & INTEGRATION
A2: TexaOne ERP Quality Assurance — Postman API Tracking
A3: Test ID | B3: Area / Feature | C3: Test case | D3: Preconditions / Test data | E3: Steps / Command | F3: Expected result | G3: Actual result / Evidence | H3: Status | I3: Priority | J3: Issue ID | K3: Executed by | L3: Execution date
A4: API-001 | B4: Authentication | C4: Login/token capture | D4: Existing Postman collection/environment | E4: POST {{baseUrl}}/auth/login | F4: Token captured and stored in accessToken variable | G4: BLOCKED: Local NestJS backend service (http://localhost:3000) is offline. Requires active server instance. | H4: BLOCKED | I4: P1 | K4: Automated Suite | L4: 2026-10-27
A5: API-COA-001 | B5: Chart of Accounts | C5: List accounts | D5: postman/finance-api.postman_collection.json #0.4 | E5: GET {{baseUrl}}/finance/accounts?limit=50 | F5: HTTP 200; array of FinanceAccount with accountType | G5: BLOCKED: Local NestJS backend service is offline. | H5: BLOCKED | I5: P1 | K5: Automated Suite | L5: 2026-10-27
A6: API-COA-002 | B6: Chart of Accounts | C6: Get account by ID | D6: Valid account ID from discovery | E6: GET {{baseUrl}}/finance/accounts/:id | F6: HTTP 200; account object with code, name, and currentBalance | G6: BLOCKED: Local NestJS backend service is offline. | H6: BLOCKED | I6: P1 | K6: Automated Suite | L6: 2026-10-27
A7: API-COA-003 | B7: Chart of Accounts | C7: Create then read back | D7: Unique accountCode | E7: POST {{baseUrl}}/finance/accounts then GET | F7: HTTP 201; persisted record with assigned id | G7: BLOCKED: Local NestJS backend service is offline. | H7: BLOCKED | I7: P1 | K7: Automated Suite | L7: 2026-10-27
A8: API-COA-004 | B8: Chart of Accounts | C8: Invalid/duplicate create | D8: Existing account code | E8: POST duplicate code payload | F8: HTTP 409 Conflict / 400 Bad Request | G8: BLOCKED: Local NestJS backend service is offline. | H8: BLOCKED | I8: P1 | K8: Automated Suite | L8: 2026-10-27
A9: API-JV-001 | B9: Journal Entries | C9: Create balanced journal | D9: Valid accounts; Sum Debits == Sum Credits | E9: POST {{baseUrl}}/finance/journal-entries | F9: HTTP 201; entryNumber assigned; status DRAFT | G9: BLOCKED: Local NestJS backend service is offline. | H9: BLOCKED | I9: P1 | K9: Automated Suite | L9: 2026-10-27
A10: API-JV-002 | B10: Journal Entries | C10: Reject unbalanced journal | D10: Debit 5000 != Credit 4000 | E10: POST unbalanced journal payload | F10: HTTP 400 Bad Request: Debits must equal Credits | G10: BLOCKED: Local NestJS backend service is offline. | H10: BLOCKED | I10: P1 | K10: Automated Suite | L10: 2026-10-27
A11: API-JV-003 | B11: Journal Entries | C11: Reject invalid account | D11: Non-existent accountId: 999999 | E11: POST journal with invalid accountId | F11: HTTP 404 / 400: Account not found or inactive | G11: BLOCKED: Local NestJS backend service is offline. | H11: BLOCKED | I11: P1 | K11: Automated Suite | L11: 2026-10-27
A12: API-JV-004 | B12: Journal Entries | C12: Duplicate request protection | D12: Same voucher payload / idempotent header | E12: Repeated submit of same voucher | F12: Idempotency prevents duplicate GL voucher rows | G12: BLOCKED: Local NestJS backend service is offline. | H12: BLOCKED | I12: P1 | K12: Automated Suite | L12: 2026-10-27
A13: API-GL-001 | B13: General Ledger | C13: Ledger filters | D13: Active accountId with transactions | E13: GET {{baseUrl}}/finance/reports/general-ledger?accountId=1 | F13: HTTP 200; transactions array with sequential runningBalance | G13: BLOCKED: Local NestJS backend service is offline. | H13: BLOCKED | I13: P1 | K13: Automated Suite | L13: 2026-10-27
A14: API-REP-001 | B14: Reports | C14: Trial Balance endpoint | D14: Balanced accounting period | E14: GET {{baseUrl}}/finance/reports/trial-balance?asOfDate=2026-10-27 | F14: HTTP 200; totalDebit equals totalCredit in summary | G14: BLOCKED: Local NestJS backend service is offline. | H14: BLOCKED | I14: P1 | K14: Automated Suite | L14: 2026-10-27
A15: API-REP-002 | B15: Reports | C15: P&L and Balance Sheet endpoints | D15: Posted transactions in period | E15: GET /finance/reports/profit-and-loss & /balance-sheet | F15: HTTP 200; Asset = Liability + Equity; Net Income correctly derived | G15: BLOCKED: Local NestJS backend service is offline. | H15: BLOCKED | I15: P1 | K15: Automated Suite | L15: 2026-10-27
... A17: API-SEC-002 | B17: Organization isolation | C17: Cross-org access denied | D17: Token from org A requesting org B entity | E17: GET record belonging to foreign org ID | F17: HTTP 403 Forbidden or 404 Not Found | G17: BLOCKED: Local NestJS backend service is offline. | H17: BLOCKED | I17: P1 | K17: Automated Suite | L17: 2026-10-27

Sheet Unit Tests
A1: FINANCE MODULE UNIT & SERVICE TEST SUITES
A2: TexaOne ERP Quality Assurance — Unit Tests Tracking
A3: Test ID | B3: Area / Feature | C3: Test case | D3: Preconditions / Test data | E3: Steps / Command | F3: Expected result | G3: Actual result / Evidence | H3: Status | I3: Priority | J3: Issue ID | K3: Executed by | L3: Execution date
A4: UNIT-001 | B4: Expenses | C4: Expenses unit tests | D4: Vitest test runner, mock Prisma repositories | E4: pnpm --filter api exec vitest run src/modules/finance/expenses | F4: All tests pass; status transitions, approvals, pay, reversal covered | G4: PASS: 3 test suites passed (expenses.service.spec.ts 24/24, expenses.repository.spec.ts 24/24, expenses-gst-itc.spec.ts 18/18 = 66 tests). | H4: PASS | I4: P1 | K4: Vitest Runner | L4: 2026-10-27
A5: UNIT-002 | B5: GST | C5: GST calculations and validation | D5: Vitest test runner, GST DTO & rule fixtures | E5: pnpm --filter api exec vitest run src/modules/finance/gst | F5: GST rate validations, proforma exclusions, ITC calculations pass | G5: PASS: 4 test suites passed (gst.service.spec.ts 10/10, gst.repository.spec.ts 7/7, gst-validation.spec.ts 16/16, gst-manual-sync.spec.ts 13/13 = 46 tests). | H5: PASS | I5: P1 | K5: Vitest Runner | L5: 2026-10-27
A6: UNIT-003 | B6: Banking | C6: Banking service tests | D6: Vitest test runner, bank transaction fixtures | E6: pnpm --filter api exec vitest run src/modules/finance/banking | F6: Bank accounts CRUD, reconciliation, transactions atomicity pass | G6: PASS: 4 test suites passed (banking.service.spec.ts 14/14, banking-validation.spec.ts 14/14, bank-accounts.repository.spec.ts 7/7, bank-transactions.repository.spec.ts 6/6 = 41 tests). | H6: PASS | I6: P1 | K6: Vitest Runner | L6: 2026-10-27
A7: UNIT-004 | B7: Payments | C7: Payments Received/Made tests | D7: Vitest test runner, payment allocations fixtures | E7: pnpm --filter api exec vitest run src/modules/finance/payments-received src/modules/finance/payments-made | F7: Multi-invoice allocations, confirmation, voiding, and posting pass | G7: PASS: 4 test suites passed (payments-received.service.spec.ts 36/36, payments-received.repository.spec.ts 11/11, payments-made.service.spec.ts 22/22, payments-made.repository.spec.ts 7/7 = 76 tests). | H7: PASS | I7: P1 | K7: Vitest Runner | L7: 2026-10-27
A8: UNIT-005 | B8: Accounting | C8: COA/Journal/GL tests | D8: Vitest test runner, double-entry fixtures | E8: pnpm --filter api exec vitest run src/modules/finance/coa src/modules/finance/journal test/finance-core-model-rules.spec.ts | F8: COA hierarchy, double-entry validation, journal voucher posting pass | G8: PASS: 5 test suites passed (accounts.service.spec.ts 16/16, accounts.repository.spec.ts 6/6, journal-entries.service.spec.ts 23/23, journal-entries.repository.spec.ts 9/9, finance-core-model-rules.spec.ts 10/10 = 64 tests). | H8: PASS | I8: P1 | K8: Vitest Runner | L8: 2026-10-27
A9: UNIT-006 | B9: Reports | C9: Trial Balance/P&L/Balance Sheet tests | D9: Vitest test runner, general ledger statements fixtures | E9: pnpm --filter api exec vitest run src/modules/finance/reports | F9: Report aggregation, balance check, sequential GL balance pass | G9: PASS: 1 test suite passed (reports.service.spec.ts 10/10 tests). | H9: PASS | I9: P1 | K9: Vitest Runner | L9: 2026-10-27
A10: UNIT-007 | B10: SCM-Finance | C10: Sales/purchase/expense integration unit tests | D10: Vitest test runner, SCM invoice/bill fixtures | E10: pnpm --filter api exec vitest run src/modules/scm/finance src/modules/finance/integration | F10: Tax synchronization, bill settlement, GL journal sync pass | G10: PASS: 3 test suites passed (finance.service.spec.ts 5/5, finance.helpers.spec.ts 6/6, sales-purchases-integration.service.spec.ts 16/16 = 27 tests). | H10: PASS | I10: P1 | K10: Vitest Runner | L10: 2026-10-27
A11: UNIT-008 | B11: Regression | C11: Full Finance suite | D11: Vitest test runner, all finance test patterns | E11: pnpm --filter api exec vitest run src/modules/finance src/modules/finance-settings src/modules/scm/finance test/finance-core-model-rules.spec.ts | F11: All 26 suites and 339 tests pass with zero regressions | G11: PASS: 26 test files passed, 339 tests passed, 0 failed in 13.13s. | H11: PASS | I11: P1 | K11: Vitest Runner | L11: 2026-10-27

Sheet Integration
A1: FINANCE INTER-MODULE INTEGRATION TESTS
A2: TexaOne ERP Quality Assurance — Integration Tracking
A3: Test ID | B3: Area / Feature | C3: Test case | D3: Preconditions / Test data | E3: Steps / Command | F3: Expected result | G3: Actual result / Evidence | H3: Status | I3: Priority | J3: Issue ID | K3: Executed by | L3: Execution date
A4: INT-001 | B4: COA → Journal | C4: Selected account reference | D4: Test account | E4: journal-entries.service.spec.ts: line validation | F4: Journal line references valid account ID; rejects missing account | G4: PASS: journal-entries.service.spec.ts verified account ID resolution and rejection of non-existent account. | H4: PASS | I4: P1 | K4: Vitest Runner | L4: 2026-10-27
A5: INT-002 | B5: Journal → GL | C5: Posted journal appears in ledger | D5: Balanced test journal | E5: reports.service.spec.ts: getGeneralLedger | F5: Posted lines and sequential running balance calculated accurately | G5: PASS: reports.service.spec.ts verified chronological running balance calculation from posted vouchers. | H5: PASS | I5: P1 | K5: Vitest Runner | L5: 2026-10-27
A6: INT-003 | B6: Journal → Trial Balance | C6: Journal contributes to TB | D6: Balanced test journal | E6: reports.service.spec.ts: getTrialBalance | F6: Debits and credits reflect posted journal; totalDebits == totalCredits | G6: PASS: reports.service.spec.ts verified that Trial Balance correctly summarizes closing debit/credit totals. | H6: PASS | I6: P1 | K6: Vitest Runner | L6: 2026-10-27
A7: INT-004 | B7: Expenses → GL | C7: Expense posting integration | D7: Approved test expense | E7: expenses.service.spec.ts: pay() workflow | F7: Generates double-entry journal voucher linking expense to cash/bank | G7: PASS: expenses.service.spec.ts verified pay() automatically creates balanced journal voucher with expense and payment accounts. | H7: PASS | I7: P1 | K7: Vitest Runner | L7: 2026-10-27
A8: INT-005 | B8: Payments → GL | C8: Payment posting integration | D8: Customer receipt confirmation | E8: payments-received.service.spec.ts: confirm() | F8: Receipt confirmation generates balanced journal voucher linking bank & AR | G8: PASS: payments-received.service.spec.ts verified confirm() creates and posts balanced GL voucher atomically. | H8: PASS | I8: P1 | K8: Vitest Runner | L8: 2026-10-27
A9: INT-006 | B9: SCM → Finance | C9: Invoice/bill GST and ledger integration | D9: SCM sales order / purchase bill | E9: sales-purchases-integration.service.spec.ts | F9: Automatic tax ledger entries and invoice settlements generated | G9: PASS: sales-purchases-integration.service.spec.ts (16 tests) verified tax split and payment posting synchronization. | H9: PASS | I9: P1 | K9: Vitest Runner | L9: 2026-10-27
A10: INT-007 | B10: Master List boundary | C10: Shared master data vs CoA | D10: Finance settings module | E10: master-list-items.service.spec.ts | F10: No duplicate ERP Master List; CoA remains strictly accounting-specific | G10: PASS: master-list-items.service.spec.ts verified category-based master items (payment_mode, expense_type) do not interfere with COA. | H10: PASS | I10: P1 | K10: Vitest Runner | L10: 2026-10-27
A11: INT-008 | B11: Persistence | C11: Create/update survives reload | D11: Approved test DB | E11: Live database read-after-write test | F11: Persisted fields and relations consistent across sessions | G11: BLOCKED: PostgreSQL database container (port 5432) is offline. Requires active Postgres connection for live persistence verification. | H11: BLOCKED | I11: P1 | K11: Automated Suite | L11: 2026-10-27

Sheet E2E Tests
A1: FINANCE BROWSER & END-TO-END AUTOMATION
A2: TexaOne ERP Quality Assurance — E2E Tests Tracking
A3: Test ID | B3: Area / Feature | C3: Test case | D3: Preconditions / Test data | E3: Steps / Command | F3: Expected result | G3: Actual result / Evidence | H3: Status | I3: Priority | J3: Issue ID | K3: Executed by | L3: Execution date
A4: E2E-001 | B4: Navigation | C4: Finance → Accounting landing page | D4: Next.js UI routes and redirects | E4: scratch/test_navigation_wiring.js | F4: Selecting Accounting or /finance opens General Ledger by default | G4: PASS: Verified that /finance and /finance/accounting redirect to /finance/general-ledger, and HorizontalNavbar routes to General Ledger. | H4: PASS | I4: P1 | K4: Test Script | L4: 2026-10-27
A5: E2E-002 | B5: COA | C5: Chart of Accounts view & tree hierarchy | D5: Playwright mock session, Finance accounts API fixtures | E5: pnpm --filter ui exec playwright test e2e/finance-accounts.spec.ts | F5: Table and Hierarchy tree views render correctly with active accounts and permissions | G5: PASS: 4/4 Playwright tests passed in finance-accounts.spec.ts (table view, tree hierarchy view, read-only permissions, and shell navigation). | H5: PASS | I5: P1 | K5: Playwright | L5: 2026-10-27
A6: E2E-003 | B6: Journal → Reports | C6: Journal voucher entry & GL browser flows | D6: Playwright mock session, Finance journal & GL API fixtures | E6: pnpm --filter ui exec playwright test e2e/finance-journal.spec.ts | F6: JV-001 through JV-007 form display, line validation, balanced voucher submission, out-of-balance warnings, running balances pass | G6: PASS: 11/11 Playwright tests passed in finance-journal.spec.ts covering JV-001 to JV-007 (dialog, table, line validation, balanced submission, out-of-balance warnings, running balances). | H6: PASS | I6: P1 | K6: Playwright | L6: 2026-10-27
A7: E2E-004 | B7: Invalid voucher | C7: Unbalanced voucher and line count validation | D7: Zod schema & form validation | E7: pnpm --filter ui exec playwright test e2e/finance-journal.spec.ts -g 'unbalanced|minimum' | F7: Submit button disabled with live difference badge; at least 2 lines required | G7: PASS: Playwright tests JV-002, JV-003 and Zod schema validation reject unbalanced vouchers (error: 'Total Debits must equal Total Credits') and single lines. | H7: PASS | I7: P1 | K7: Playwright | L7: 2026-10-27
A8: E2E-005 | B8: Finance Settings & Navigation | C8: Finance master tabs, expense types, and sub-tab routing | D8: Playwright mock session, Finance settings fixtures | E8: pnpm --filter ui exec playwright test e2e/finance-settings.spec.ts & scratch/test_navigation_wiring.js | F8: All 4 accounting sub-tabs accessible; settings master tabs, chips add/delete pass | G8: PASS: 4/4 Playwright tests passed in finance-settings.spec.ts (master tabs, expense types chips add/delete, permission guards) and navigation wiring verified. | H8: PASS | I8: P1 | K8: Playwright | L8: 2026-10-27
A9: E2E-006 | B9: Responsive UI | C9: Supported viewports & layout containers | D9: Responsive grid layout, Next.js UI typecheck & lint | E9: pnpm --filter ui run typecheck && pnpm --filter ui run lint && visual container audit | F9: No blocking overflow; form cards avoid overflow-hidden; Nunito Sans preserved | G9: NOT RUN: Responsive layout audit for mobile/tablet viewports prioritized for manual visual walkthrough. | H9: NOT RUN | I9: P2

Sheet Database Checks
A1: FINANCE DATABASE SCHEMA & CONSTRAINTS AUDIT
A2: TexaOne ERP Quality Assurance — Database Checks Tracking
A3: Test ID | B3: Area / Feature | C3: Test case | D3: Preconditions / Test data | E3: Steps / Command | F3: Expected result | G3: Actual result / Evidence | H3: Status | I3: Priority | J3: Issue ID | K3: Executed by | L3: Execution date
A4: DB-001 | B4: COA schema | C4: Constraints and uniqueness | D4: packages/database/prisma/schema.prisma | E4: Inspect FinanceAccount model and @@unique([organizationId, accountCode]) | F4: Account codes scoped and unique per organization | G4: PASS: Schema defines @@unique([organizationId, accountCode]) and foreign key to parentAccount. | H4: PASS | I4: P1 | K4: Schema Audit | L4: 2026-10-27
A5: DB-002 | B5: Journal schema | C5: Journal header and lines atomicity | D5: FinanceJournalEntry & FinanceJournalLine models | E5: test/finance-core-model-rules.spec.ts | F5: Voucher and lines persist atomically with foreign keys and cascade delete | G5: PASS: Model rules confirm atomic relationship with entryId FK and organizationId tenant index. | H5: PASS | I5: P1 | K5: Schema Audit | L5: 2026-10-27
A6: DB-003 | B6: Accounting integrity | C6: Debit/credit persistence | D6: finance-core-model-rules.spec.ts | E6: Inspect journal entry totalDebit & totalCredit fields | F6: Stored debits equal credits on posted entries | G6: PASS: Verified totalDebit and totalCredit are stored as Decimal(15,2) with balance enforcement. | H6: PASS | I6: P1 | K6: Schema Audit | L6: 2026-10-27
A7: DB-004 | B7: Relations | C7: Account and parent relations | D7: FinanceAccount self-relation | E7: Inspect parentAccount and subAccounts in schema.prisma | F7: Valid tree hierarchy; self-referencing foreign key configured | G7: PASS: Verified parentAccount FinanceAccount? @relation("AccountHierarchy", fields: [parentAccountId], references: [id]). | H7: PASS | I7: P1 | K7: Schema Audit | L7: 2026-10-27
A8: DB-005 | B8: Tenant isolation | C8: Organization-scoped data | D8: All finance Prisma models | E8: Check organizationId indexed in all finance tables | F8: All queries strictly scoped by organizationId; no cross-tenant reads | G8: PASS: Verified organizationId indexed on FinanceAccount, FinanceJournalEntry, FinanceExpense, FinancePaymentReceived, etc. | H8: PASS | I8: P1 | K8: Schema Audit | L8: 2026-10-27
A9: DB-006 | B9: Migrations | C9: Finance migration status | D9: packages/database/prisma/migrations | E9: Inspect migration files for finance tables and constraints | F9: All migrations valid SQL; no orphaned tables or missing constraints | G9: PASS: All 7 finance table migrations verified in packages/database/prisma/migrations. | H9: PASS | I9: P1 | K9: Schema Audit | L9: 2026-10-27

Sheet Security
A1: FINANCE SECURITY, AUTH & TENANT ISOLATION TESTS
A2: TexaOne ERP Quality Assurance — Security Tracking
A3: Test ID | B3: Area / Feature | C3: Test case | D3: Preconditions / Test data | E3: Steps / Command | F3: Expected result | G3: Actual result / Evidence | H3: Status | I3: Priority | J3: Issue ID | K3: Executed by | L3: Execution date
A4: SEC-001 | B4: Authentication | C4: Unauthenticated Finance API | D4: JwtAuthGuard in apps/api | E4: jwt-auth.guard.spec.ts: verify token requirement | F4: Calls without valid JWT are rejected with 401 Unauthorized | G4: PASS: jwt-auth.guard.spec.ts (10 tests) passed, verifying unauthenticated request rejection. | H4: PASS | I4: P1 | K4: Vitest Runner | L4: 2026-10-27
A5: SEC-002 | B5: Authorization | C5: Role permissions | D5: PermissionsGuard & role catalog | E5: permissions.guard.spec.ts & default-roles.test.ts | F5: Only permitted roles can read/write/post journal entries and expenses | G5: PASS: permissions.guard.spec.ts (18 tests) & default-roles.test.ts (65 tests) passed. | H5: PASS | I5: P1 | K5: Vitest Runner | L5: 2026-10-27
A6: SEC-003 | B6: Tenant isolation | C6: Cross-org ID tampering | D6: TenantContextService & @OrgScoped() decorator | E6: team-where.spec.ts & tenant-where.spec.ts | F6: Tenant context strictly enforces WHERE organizationId = callerOrgId | G6: PASS: team-where.spec.ts (25 tests) & tenant-where.spec.ts (4 tests) passed. | H6: PASS | I6: P1 | K6: Vitest Runner | L6: 2026-10-27
A7: SEC-004 | B7: Input validation | C7: Malformed IDs/amounts/dates | D7: Class-validator DTOs | E7: banking-validation.spec.ts & gst-validation.spec.ts | F7: Negative amounts, invalid dates, and malformed IDs rejected with 400 | G7: PASS: banking-validation.spec.ts (14 tests) & gst-validation.spec.ts (16 tests) passed. | H7: PASS | I7: P1 | K7: Vitest Runner | L7: 2026-10-27
A8: SEC-005 | B8: Auditability | C8: Accounting changes audit trail | D8: AuditWriter in apps/api | E8: audit-writer.spec.ts & journal post metadata | F8: postedBy, postedAt, createdBy timestamps immutably preserved | G8: PASS: audit-writer.spec.ts (13 tests) passed; journal post actions record immutable user/timestamp stamps. | H8: PASS | I8: P1 | K8: Vitest Runner | L8: 2026-10-27

Sheet Regression
A1: FINANCE MODULE REGRESSION SUITE
A2: TexaOne ERP Quality Assurance — Regression Tracking
A3: Test ID | B3: Area / Feature | C3: Test case | D3: Preconditions / Test data | E3: Steps / Command | F3: Expected result | G3: Actual result / Evidence | H3: Status | I3: Priority | J3: Issue ID | K3: Executed by | L3: Execution date
A4: REG-001 | B4: Finance | C4: Expenses regression | D4: Existing test suite | E4: pnpm --filter api exec vitest run src/modules/finance/expenses | F4: All expenses tests continue to pass | G4: PASS: 66/66 tests passed with 0 failures. | H4: PASS | I4: P1 | K4: Vitest Runner | L4: 2026-10-27
A5: REG-002 | B5: Finance | C5: Payments Received regression | D5: Existing test suite | E5: pnpm --filter api exec vitest run src/modules/finance/payments-received | F5: All payments received tests continue to pass | G5: PASS: 47/47 tests passed with 0 failures. | H5: PASS | I5: P1 | K5: Vitest Runner | L5: 2026-10-27
A6: REG-003 | B6: Finance | C6: Payments Made regression | D6: Existing test suite | E6: pnpm --filter api exec vitest run src/modules/finance/payments-made | F6: All payments made tests continue to pass | G6: PASS: 29/29 tests passed with 0 failures. | H6: PASS | I6: P1 | K6: Vitest Runner | L6: 2026-10-27
A7: REG-004 | B7: Finance | C7: Banking regression | D7: Existing test suite | E7: pnpm --filter api exec vitest run src/modules/finance/banking | F7: All banking tests continue to pass | G7: PASS: 41/41 tests passed with 0 failures. | H7: PASS | I7: P1 | K7: Vitest Runner | L7: 2026-10-27
A8: REG-005 | B8: Finance | C8: GST regression | D8: Existing test suite | E8: pnpm --filter api exec vitest run src/modules/finance/gst | F8: All GST tests continue to pass | G8: PASS: 46/46 tests passed with 0 failures. | H8: PASS | I8: P1 | K8: Vitest Runner | L8: 2026-10-27
A9: REG-006 | B9: Finance | C9: Accounting/reports regression | D9: Existing test suite | E9: pnpm --filter api exec vitest run src/modules/finance/coa src/modules/finance/journal src/modules/finance/reports test/finance-core-model-rules.spec.ts | F9: All COA, Journal, GL and report tests pass | G9: PASS: 74/74 tests passed with 0 failures. | H9: PASS | I9: P1 | K9: Vitest Runner | L9: 2026-10-27
A10: REG-007 | B10: SCM | C10: SCM-Finance GST/ITC regression | D10: Existing test suite | E10: pnpm --filter api exec vitest run src/modules/scm/finance src/modules/finance/integration | F10: All SCM-Finance integration tests pass | G10: PASS: 27/27 tests passed with 0 failures. | H10: PASS | I10: P1 | K10: Vitest Runner | L10: 2026-10-27

Sheet Bug Log
A1: FINANCE MODULE DEFECT & BUG TRACKER
A2: Tracked issues from manual walkthroughs, automated test failures, and integration audits
A3: Issue ID | B3: Date | C3: Summary | D3: Page / Environment | E3: Steps to Reproduce | F3: Expected Result | G3: Actual Result / Evidence | H3: Status | I3: Severity | J3: Owner | K3: Fix Version | L3: Retest Status
A4: BUG-001 | B4: 2026-10-24 | C4: Expense creation failed when GST ITC asset account 1300 was not configured | D4: Finance → Expenses | E4: Create standard operating expense without recoverable ITC when account 1300 is not seeded | F4: Ordinary expenses create successfully without coupling to GST ITC asset account | G4: 500 Internal Server Error (P2025: Record to connect not found on account 1300) | H4: RESOLVED | I4: HIGH | J4: Finance Core | K4: v1.2.0-finance | L4: VERIFIED
A5: BUG-002 | B5: 2026-10-26 | C5: Husky pre-commit hook lint failure due to scratch scripts and loose spec typing | D5: Pre-commit Git Hook | E5: Run git commit on feature/finance branch with scratch scripts present | F5: Pre-commit ESLint check completes cleanly on production packages; scratch/ ignored | G5: Husky pre-commit hook failed with 83 ESLint errors (require-imports, explicit-any) | H5: RESOLVED | I5: MEDIUM | J5: DevOps / Core | K5: v1.2.0-finance | L5: VERIFIED
A6: BUG-003 | B6: 2026-10-27 | C6: Playwright E2E redirected to /login on page.goto due to unmocked /auth/refresh & missing hr.workspace.access | D6: Finance E2E Suite | E6: Execute Playwright tests navigating to /finance routes via page.goto | F6: Authenticated session preserved via Next.js session restore; landing page rendered | G6: Unmocked POST /auth/refresh cleared session and redirected to /login | H6: RESOLVED | I6: MEDIUM | J6: QA Automation | K6: v1.2.0-finance | L6: VERIFIED
